odoo/addons/sale_blanket_order_commitment_date/LICENSE
odoo/addons/sale_blanket_order_commitment_date/README.rst
odoo/addons/sale_blanket_order_commitment_date/__init__.py
odoo/addons/sale_blanket_order_commitment_date/__manifest__.py
odoo/addons/sale_blanket_order_commitment_date/images/screen.png
odoo/addons/sale_blanket_order_commitment_date/static/description/icon.png
odoo/addons/sale_blanket_order_commitment_date/static/description/index.html
odoo/addons/sale_blanket_order_commitment_date/tests/TEST_INSTRUCTIONS.rst
odoo/addons/sale_blanket_order_commitment_date/wizard/__init__.py
odoo/addons/sale_blanket_order_commitment_date/wizard/create_sale_orders.py
odoo_addon_sale_blanket_order_commitment_date-16.0.1.0.0.dist-info/METADATA
odoo_addon_sale_blanket_order_commitment_date-16.0.1.0.0.dist-info/WHEEL
odoo_addon_sale_blanket_order_commitment_date-16.0.1.0.0.dist-info/top_level.txt
odoo_addon_sale_blanket_order_commitment_date-16.0.1.0.0.dist-info/RECORD
