Metadata-Version: 2.1
Name: odoo-addon-sale_blanket_order_commitment_date
Version: 16.0.1.0.0
Requires-Python: >=3.10
Requires-Dist: odoo-addon-sale_blanket_order>=16.0dev,<16.1dev
Requires-Dist: odoo-addon-sale_order_line_date>=16.0dev,<16.1dev
Requires-Dist: odoo>=16.0a,<16.1dev
Summary: Copies the blanket order line scheduled date to sale line commitment date.
Home-page: https://www.mint-system.ch/
License: AGPL-3
Author: Mint System GmbH
Classifier: Programming Language :: Python
Classifier: Framework :: Odoo
Classifier: Framework :: Odoo :: 16.0
Classifier: License :: OSI Approved :: GNU Affero General Public License v3
